example_1/example_1.v
// Verilog model of circuit of Figure 3.35 in Digital Systems 5th ed.

module example_1(A, B, C, D, E);

   output D, E;
   input  A, B, C;
   wire   w1;

   and G1(w1, A, B);
   not G2(E, w1);
   xor  G3(D, A, C);


endmodule

example_1/example_1_tb.v
// Verilog test bench for example_3_1
//`timescale 1ns/100ps
//`include "example_1.v"

module example_1_tb;

   wire A, B, C, D, E;
   integer k=0;

   assign {A,B,C} = k;
   example_1 the_circuit(A, B, C, D, E);

   initial begin

      $dumpfile("example_1.vcd");
      $dumpvars(0, example_1_tb);

      for (k=0; k<8; k=k+1)
        #10 $display("done testing case %d", k);

      $finish;

   end

endmodule

example_1/example_1.vcd
$date
	Tue Sep 19 12:35:44 2017
$end
$version
	Icarus Verilog
$end
$timescale
	1s
$end
$scope module example_1_tb $end
$var wire 1 ! E $end
$var wire 1 " D $end
$var wire 1 # C $end
$var wire 1 $ B $end
$var wire 1 % A $end
$var integer 32 & k [31:0] $end
$scope module the_circuit $end
$var wire 1 % A $end
$var wire 1 $ B $end
$var wire 1 # C $end
$var wire 1 " D $end
$var wire 1 ! E $end
$var wire 1 ' w1 $end
$upscope $end
$upscope $end
$enddefinitions $end
#0
$dumpvars
0'
b0 &
0%
0$
0#
0"
1!
$end
#10
1"
1#
b1 &
#20
0"
0#
1$
b10 &
#30
1"
1#
b11 &
#40
0#
0$
1%
b100 &
#50
0"
1#
b101 &
#60
0!
1"
1'
0#
1$
b110 &
#70
0"
1#
b111 &
#80
1!
0'
0#
0$
0%
b1000 &
